Tool4ASN/__init__.py
Tool4ASN/__main__.py
Tool4ASN-0.0.5.dist-info/LICENSE
Tool4ASN-0.0.5.dist-info/METADATA
Tool4ASN-0.0.5.dist-info/WHEEL
Tool4ASN-0.0.5.dist-info/entry_points.txt
Tool4ASN-0.0.5.dist-info/top_level.txt
Tool4ASN-0.0.5.dist-info/RECORD
