Metadata-Version: 2.1
Name: Tool4ASN
Version: 0.0.5
Summary: Python module able to download a file from FTP and subset it using time-range,bounding-box,variables and depths
Home-page: https://github.com/carmelosammarco/Tool4ASN
Author: Carmelo Sammarco
Author-email: sammarcocarmelo@gmail.com
License: gpl-3.0
Platform: OS Independent
Classifier: Development Status :: 3 - Alpha
Classifier: Intended Audience :: Science/Research
Classifier: Topic :: Scientific/Engineering
Classifier: Programming Language :: Python :: 3.6
Requires-Python: >=3
Requires-Dist: ftputil (>=3.4)
